{
  "partnerLogos": [
    { "src": "/assets/EMI.png", "alt": "EMI Logo" },
    { "src": "/assets/ECC.png", "alt": "Ethiopian Chamber of Commerce Logo" },
    { "src": "/assets/icap.svg", "alt": "ICAP Global Health Logo" },
    { "src": "/assets/mit.png", "alt": "MIT Logo" },
    { "src": "/assets/II.png", "alt": "Industry Information System Logo" },
    { "src": "/assets/ECC.png", "alt": "Ethiopian Chamber of Commerce Logo" },
    { "src": "/assets/icap.svg", "alt": "ICAP Global Health Logo" },
    { "src": "/assets/mit.png", "alt": "MIT Logo" }
  ]
}
